Workbook

Sheet How to Play
A1: HOW TO PLAY — FUEL MARKET SQUEEZE
A3: WHAT THIS IS
A4: A hand-played model of your galactic fuel market. You make the decisions for all five guilds, turn by
A5: turn, on the Simulation sheet. The sheet computes the price and the consequences. The goal of Phase 0
A6: is NOT to build the game — it is to find out whether the fuel economy is TENSE and FUN before you write
A7: any real code.
A9: THE FIVE GUILDS (archetypes from your design doc)
A10: Refinery Combine — Refiner. Produces lots of fuel, wants it flowing, profits from processing.
A11: Vantar Trust — Stockpiler. Buys fuel up and HOLDS it to create scarcity, then dumps at high prices.
A12: Orun Compact — Trader. Buys low, sells high, profits from movement.
A13: Dracis Concern — Manufacturer. Thirsty factories (needs 12/turn). The guild that SUFFERS in a squeeze.
A14: Ilyra Holdings — Small guild. Low needs, thin wallet. Your 'survival floor' test case.
... A45: • Watch the 'Over-demand?' row — if it says OVER, players tried to buy fuel that doesn't exist; reduce a Buy.

Sheet Setup
A1: FUEL MARKET SIMULATOR — SETUP & LEVERS
A2: Blue numbers are levers you can change. Everything on the Simulation sheet recalculates from these.
A3: Base price ($/unit at equilibrium) | B3: 5
A4: Target reserve (equilibrium stockpile) | B4: 30
A5: Price sensitivity (exponent) | B5: 0.6
A6: Price floor ($) | B6: 2
A7: Price ceiling ($) | B7: 40
A8: Income per guild per turn ($) | B8: 100
A9: Starting market stockpile | B9: 30
A11: Guild | B11: Archetype | C11: Fuel need/turn | D11: Production capacity | E11: Starting credits ($) | F11: Starting hoard
A12: Refinery Combine | B12: Refiner | C12: 8 | D12: 40 | E12: 120 | F12: 0
A13: Vantar Trust | B13: Stockpiler | C13: 5 | D13: 6 | E13: 250 | F13: 0
A14: Orun Compact | B14: Trader | C14: 4 | D14: 4 | E14: 120 | F14: 0
A15: Dracis Concern | B15: Manufacturer | C15: 12 | D15: 8 | E15: 100 | F15: 0
A16: Ilyra Holdings | B16: Small guild | C16: 3 | D16: 3 | E16: 60 | F16: 0

Sheet Simulation
A1: FUEL MARKET SIMULATOR — HAND-PLAYED
A2: Yellow cells are your decisions each turn (Produce / Buy / Sell). Watch the PRICE row and the SHORTFALL rows.
A3: TURN → | B3: 1 | C3: 2 | D3: 3 | E3: 4 | F3: 5 | G3: 6 | H3: 7 | I3: 8 | J3: 9 | K3: 10 | L3: 11 | M3: 12
A4: Stockpile — start | B4: =Setup!$B$9 -> 30 | C4: =B9 -> 30 | D4: =C9 -> 30 | E4: =D9 -> 30 | F4: =E9 -> 17 | G4: =F9 -> 4 | H4: =G9 -> 1 | I4: =H9 -> 4 | J4: =I9 -> 29 | ... M4: =L9 -> 29
A5: Fuel to market (Σ produce + sell) | B5: =B12+B14+B19+B21+B26+B28+B33+B35+B40+B42 -> 32 | C5: =C12+C14+C19+C21+C26+C28+C33+C35+C40+C42 -> 32 | D5: =D12+D14+D19+D21+D26+D28+D33+D35+D40+D42 -> 32 | E5: =E12+E14+E19+E21+E26+E28+E33+E35+E40+E42 -> 32 | F5: =F12+F14+F19+F21+F26+F28+F33+F35+F40+F42 -> 32 | G5: =G12+G14+G19+G21+G26+G28+G33+G35+G40+G42 -> 32 | H5: =H12+H14+H19+H21+H26+H28+H33+H35+H40+H42 -> 32 | I5: =I12+I14+I19+I21+I26+I28+I33+I35+I40+I42 -> 50 | ... M5: =M12+M14+M19+M21+M26+M28+M33+M35+M40+M42 -> 32
A6: Available fuel | B6: =B4+B5 -> 62 | C6: =C4+C5 -> 62 | D6: =D4+D5 -> 62 | E6: =E4+E5 -> 62 | F6: =F4+F5 -> 49 | G6: =G4+G5 -> 36 | H6: =H4+H5 -> 33 | I6: =I4+I5 -> 54 | ... M6: =M4+M5 -> 61
A7: PRICE ($ / unit) | B7: =MIN(Setup!$B$7,MAX(Setup!$B$6,Setup!$B$3*(Setup!$B$4/MAX(1,B4))^Setup!$B$5)) -> 5 | C7: =MIN(Setup!$B$7,MAX(Setup!$B$6,Setup!$B$3*(Setup!$B$4/MAX(1,C4))^Setup!$B$5)) -> 5 | D7: =MIN(Setup!$B$7,MAX(Setup!$B$6,Setup!$B$3*(Setup!$B$4/MAX(1,D4))^Setup!$B$5)) -> 5 | E7: =MIN(Setup!$B$7,MAX(Setup!$B$6,Setup!$B$3*(Setup!$B$4/MAX(1,E4))^Setup!$B$5)) -> 5 | F7: =MIN(Setup!$B$7,MAX(Setup!$B$6,Setup!$B$3*(Setup!$B$4/MAX(1,F4))^Setup!$B$5)) -> 7.0302927 | G7: =MIN(Setup!$B$7,MAX(Setup!$B$6,Setup!$B$3*(Setup!$B$4/MAX(1,G4))^Setup!$B$5)) -> 16.74969 | H7: =MIN(Setup!$B$7,MAX(Setup!$B$6,Setup!$B$3*(Setup!$B$4/MAX(1,H4))^Setup!$B$5)) -> 38.480682 | I7: =MIN(Setup!$B$7,MAX(Setup!$B$6,Setup!$B$3*(Setup!$B$4/MAX(1,I4))^Setup!$B$5)) -> 16.74969 | ... M7: =MIN(Setup!$B$7,MAX(Setup!$B$6,Setup!$B$3*(Setup!$B$4/MAX(1,M4))^Setup!$B$5)) -> 5.1027461
A8: Total bought (Σ buy) | B8: =B13+B20+B27+B34+B41 -> 32 | C8: =C13+C20+C27+C34+C41 -> 32 | D8: =D13+D20+D27+D34+D41 -> 32 | E8: =E13+E20+E27+E34+E41 -> 45 | F8: =F13+F20+F27+F34+F41 -> 45 | G8: =G13+G20+G27+G34+G41 -> 35 | H8: =H13+H20+H27+H34+H41 -> 29 | I8: =I13+I20+I27+I34+I41 -> 25 | ... M8: =M13+M20+M27+M34+M41 -> 32
A9: Stockpile — end | B9: =B6-B8 -> 30 | C9: =C6-C8 -> 30 | D9: =D6-D8 -> 30 | E9: =E6-E8 -> 17 | F9: =F6-F8 -> 4 | G9: =G6-G8 -> 1 | H9: =H6-H8 -> 4 | I9: =I6-I8 -> 29 | ... M9: =M6-M8 -> 29
A10: Over-demand? (buy > available) | B10: =IF(B8>B6,"OVER","ok") -> ok | C10: =IF(C8>C6,"OVER","ok") -> ok | D10: =IF(D8>D6,"OVER","ok") -> ok | E10: =IF(E8>E6,"OVER","ok") -> ok | F10: =IF(F8>F6,"OVER","ok") -> ok | G10: =IF(G8>G6,"OVER","ok") -> ok | H10: =IF(H8>H6,"OVER","ok") -> ok | I10: =IF(I8>I6,"OVER","ok") -> ok | ... M10: =IF(M8>M6,"OVER","ok") -> ok
A12: Refinery Combine — Produce | B12: 24 | C12: 24 | D12: 24 | E12: 24 | F12: 24 | G12: 24 | H12: 24 | I12: 24 | J12: 24 | K12: 24 | L12: 24 | M12: 24
A13: — Buy | B13: 8 | C13: 8 | D13: 8 | E13: 8 | F13: 8 | G13: 8 | H13: 8 | I13: 8 | J13: 8 | K13: 8 | L13: 8 | M13: 8
A14: — Sell (from hoard) | B14: 0 | C14: 0 | D14: 0 | E14: 0 | F14: 0 | G14: 0 | H14: 0 | I14: 0 | J14: 0 | K14: 0 | L14: 0 | M14: 0
A15: — Credits ($) | B15: =Setup!$E$12+Setup!$B$8-B13*B7+(B12+B14)*B7 -> 300 | C15: =B15+Setup!$B$8-C13*C7+(C12+C14)*C7 -> 480 | D15: =C15+Setup!$B$8-D13*D7+(D12+D14)*D7 -> 660 | E15: =D15+Setup!$B$8-E13*E7+(E12+E14)*E7 -> 840 | F15: =E15+Setup!$B$8-F13*F7+(F12+F14)*F7 -> 1052.4847 | G15: =F15+Setup!$B$8-G13*G7+(G12+G14)*G7 -> 1420.4797 | H15: =G15+Setup!$B$8-H13*H7+(H12+H14)*H7 -> 2136.1706 | I15: =H15+Setup!$B$8-I13*I7+(I12+I14)*I7 -> 2504.1657 | J15: =I15+Setup!$B$8-J13*J7+(J12+J14)*J7 -> 2685.8096 | ... M15: =L15+Setup!$B$8-M13*M7+(M12+M14)*M7 -> 3230.7414
A16: — Hoard | B16: =MAX(0,Setup!$F$12+B13-Setup!$C$12-B14) -> 0 | C16: =MAX(0,B16+C13-Setup!$C$12-C14) -> 0 | D16: =MAX(0,C16+D13-Setup!$C$12-D14) -> 0 | E16: =MAX(0,D16+E13-Setup!$C$12-E14) -> 0 | F16: =MAX(0,E16+F13-Setup!$C$12-F14) -> 0 | G16: =MAX(0,F16+G13-Setup!$C$12-G14) -> 0 | H16: =MAX(0,G16+H13-Setup!$C$12-H14) -> 0 | I16: =MAX(0,H16+I13-Setup!$C$12-I14) -> 0 | J16: =MAX(0,I16+J13-Setup!$C$12-J14) -> 0 | ... M16: =MAX(0,L16+M13-Setup!$C$12-M14) -> 0
A17: — Shortfall | B17: =MAX(0,Setup!$C$12+B14-Setup!$F$12-B13) -> 0 | C17: =MAX(0,Setup!$C$12+C14-B16-C13) -> 0 | D17: =MAX(0,Setup!$C$12+D14-C16-D13) -> 0 | E17: =MAX(0,Setup!$C$12+E14-D16-E13) -> 0 | F17: =MAX(0,Setup!$C$12+F14-E16-F13) -> 0 | G17: =MAX(0,Setup!$C$12+G14-F16-G13) -> 0 | H17: =MAX(0,Setup!$C$12+H14-G16-H13) -> 0 | I17: =MAX(0,Setup!$C$12+I14-H16-I13) -> 0 | J17: =MAX(0,Setup!$C$12+J14-I16-J13) -> 0 | ... M17: =MAX(0,Setup!$C$12+M14-L16-M13) -> 0
A19: Vantar Trust — Produce | B19: 0 | C19: 0 | D19: 0 | E19: 0 | F19: 0 | G19: 0 | H19: 0 | I19: 0 | J19: 0 | K19: 0 | L19: 0 | M19: 0
A20: — Buy | B20: 5 | C20: 5 | D20: 5 | E20: 18 | F20: 18 | G20: 12 | H20: 8 | I20: 0 | J20: 5 | K20: 5 | L20: 5 | M20: 5
A21: — Sell (from hoard) | B21: 0 | C21: 0 | D21: 0 | E21: 0 | F21: 0 | G21: 0 | H21: 0 | I21: 18 | J21: 0 | K21: 0 | L21: 0 | M21: 0
A22: — Credits ($) | B22: =Setup!$E$13+Setup!$B$8-B20*B7+(B19+B21)*B7 -> 325 | C22: =B22+Setup!$B$8-C20*C7+(C19+C21)*C7 -> 400 | D22: =C22+Setup!$B$8-D20*D7+(D19+D21)*D7 -> 475 | E22: =D22+Setup!$B$8-E20*E7+(E19+E21)*E7 -> 485 | F22: =E22+Setup!$B$8-F20*F7+(F19+F21)*F7 -> 458.45473 | G22: =F22+Setup!$B$8-G20*G7+(G19+G21)*G7 -> 357.45846 | H22: =G22+Setup!$B$8-H20*H7+(H19+H21)*H7 -> 149.613 | I22: =H22+Setup!$B$8-I20*I7+(I19+I21)*I7 -> 551.10742 | J22: =I22+Setup!$B$8-J20*J7+(J19+J21)*J7 -> 625.59369 | ... M22: =L22+Setup!$B$8-M20*M7+(M19+M21)*M7 -> 849.05249
A23: — Hoard | B23: =MAX(0,Setup!$F$13+B20-Setup!$C$13-B21) -> 0 | C23: =MAX(0,B23+C20-Setup!$C$13-C21) -> 0 | D23: =MAX(0,C23+D20-Setup!$C$13-D21) -> 0 | E23: =MAX(0,D23+E20-Setup!$C$13-E21) -> 13 | F23: =MAX(0,E23+F20-Setup!$C$13-F21) -> 26 | G23: =MAX(0,F23+G20-Setup!$C$13-G21) -> 33 | H23: =MAX(0,G23+H20-Setup!$C$13-H21) -> 36 | I23: =MAX(0,H23+I20-Setup!$C$13-I21) -> 13 | J23: =MAX(0,I23+J20-Setup!$C$13-J21) -> 13 | ... M23: =MAX(0,L23+M20-Setup!$C$13-M21) -> 13
A24: — Shortfall | B24: =MAX(0,Setup!$C$13+B21-Setup!$F$13-B20) -> 0 | C24: =MAX(0,Setup!$C$13+C21-B23-C20) -> 0 | D24: =MAX(0,Setup!$C$13+D21-C23-D20) -> 0 | E24: =MAX(0,Setup!$C$13+E21-D23-E20) -> 0 | F24: =MAX(0,Setup!$C$13+F21-E23-F20) -> 0 | G24: =MAX(0,Setup!$C$13+G21-F23-G20) -> 0 | H24: =MAX(0,Setup!$C$13+H21-G23-H20) -> 0 | I24: =MAX(0,Setup!$C$13+I21-H23-I20) -> 0 | J24: =MAX(0,Setup!$C$13+J21-I23-J20) -> 0 | ... M24: =MAX(0,Setup!$C$13+M21-L23-M20) -> 0
A26: Orun Compact — Produce | B26: 0 | C26: 0 | D26: 0 | E26: 0 | F26: 0 | G26: 0 | H26: 0 | I26: 0 | J26: 0 | K26: 0 | L26: 0 | M26: 0
A27: — Buy | B27: 4 | C27: 4 | D27: 4 | E27: 4 | F27: 4 | G27: 6 | H27: 6 | I27: 4 | J27: 4 | K27: 4 | L27: 4 | M27: 4
A28: — Sell (from hoard) | B28: 0 | C28: 0 | D28: 0 | E28: 0 | F28: 0 | G28: 0 | H28: 0 | I28: 0 | J28: 0 | K28: 0 | L28: 0 | M28: 0
A29: — Credits ($) | B29: =Setup!$E$14+Setup!$B$8-B27*B7+(B26+B28)*B7 -> 200 | C29: =B29+Setup!$B$8-C27*C7+(C26+C28)*C7 -> 280 | D29: =C29+Setup!$B$8-D27*D7+(D26+D28)*D7 -> 360 | E29: =D29+Setup!$B$8-E27*E7+(E26+E28)*E7 -> 440 | F29: =E29+Setup!$B$8-F27*F7+(F26+F28)*F7 -> 511.87883 | G29: =F29+Setup!$B$8-G27*G7+(G26+G28)*G7 -> 511.38069 | H29: =G29+Setup!$B$8-H27*H7+(H26+H28)*H7 -> 380.4966 | I29: =H29+Setup!$B$8-I27*I7+(I26+I28)*I7 -> 413.49784 | J29: =I29+Setup!$B$8-J27*J7+(J26+J28)*J7 -> 493.08686 | ... M29: =L29+Setup!$B$8-M27*M7+(M26+M28)*M7 -> 731.85391
A30: — Hoard | B30: =MAX(0,Setup!$F$14+B27-Setup!$C$14-B28) -> 0 | C30: =MAX(0,B30+C27-Setup!$C$14-C28) -> 0 | D30: =MAX(0,C30+D27-Setup!$C$14-D28) -> 0 | E30: =MAX(0,D30+E27-Setup!$C$14-E28) -> 0 | F30: =MAX(0,E30+F27-Setup!$C$14-F28) -> 0 | G30: =MAX(0,F30+G27-Setup!$C$14-G28) -> 2 | H30: =MAX(0,G30+H27-Setup!$C$14-H28) -> 4 | I30: =MAX(0,H30+I27-Setup!$C$14-I28) -> 4 | J30: =MAX(0,I30+J27-Setup!$C$14-J28) -> 4 | ... M30: =MAX(0,L30+M27-Setup!$C$14-M28) -> 4
A31: — Shortfall | B31: =MAX(0,Setup!$C$14+B28-Setup!$F$14-B27) -> 0 | C31: =MAX(0,Setup!$C$14+C28-B30-C27) -> 0 | D31: =MAX(0,Setup!$C$14+D28-C30-D27) -> 0 | E31: =MAX(0,Setup!$C$14+E28-D30-E27) -> 0 | F31: =MAX(0,Setup!$C$14+F28-E30-F27) -> 0 | G31: =MAX(0,Setup!$C$14+G28-F30-G27) -> 0 | H31: =MAX(0,Setup!$C$14+H28-G30-H27) -> 0 | I31: =MAX(0,Setup!$C$14+I28-H30-I27) -> 0 | J31: =MAX(0,Setup!$C$14+J28-I30-J27) -> 0 | ... M31: =MAX(0,Setup!$C$14+M28-L30-M27) -> 0
A33: Dracis Concern — Produce | B33: 5 | C33: 5 | D33: 5 | E33: 5 | F33: 5 | G33: 5 | H33: 5 | I33: 5 | J33: 5 | K33: 5 | L33: 5 | M33: 5
A34: — Buy | B34: 12 | C34: 12 | D34: 12 | E34: 12 | F34: 12 | G34: 6 | H34: 5 | I34: 10 | J34: 12 | K34: 12 | L34: 12 | M34: 12
A35: — Sell (from hoard) | B35: 0 | C35: 0 | D35: 0 | E35: 0 | F35: 0 | G35: 0 | H35: 0 | I35: 0 | J35: 0 | K35: 0 | L35: 0 | M35: 0
A36: — Credits ($) | B36: =Setup!$E$15+Setup!$B$8-B34*B7+(B33+B35)*B7 -> 165 | C36: =B36+Setup!$B$8-C34*C7+(C33+C35)*C7 -> 230 | D36: =C36+Setup!$B$8-D34*D7+(D33+D35)*D7 -> 295 | E36: =D36+Setup!$B$8-E34*E7+(E33+E35)*E7 -> 360 | F36: =E36+Setup!$B$8-F34*F7+(F33+F35)*F7 -> 410.78795 | G36: =F36+Setup!$B$8-G34*G7+(G33+G35)*G7 -> 494.03826 | H36: =G36+Setup!$B$8-H34*H7+(H33+H35)*H7 -> 594.03826 | I36: =H36+Setup!$B$8-I34*I7+(I33+I35)*I7 -> 610.28981 | J36: =I36+Setup!$B$8-J34*J7+(J33+J35)*J7 -> 674.57059 | ... M36: =L36+Setup!$B$8-M34*M7+(M33+M35)*M7 -> 867.41292
A37: — Hoard | B37: =MAX(0,Setup!$F$15+B34-Setup!$C$15-B35) -> 0 | C37: =MAX(0,B37+C34-Setup!$C$15-C35) -> 0 | D37: =MAX(0,C37+D34-Setup!$C$15-D35) -> 0 | E37: =MAX(0,D37+E34-Setup!$C$15-E35) -> 0 | F37: =MAX(0,E37+F34-Setup!$C$15-F35) -> 0 | G37: =MAX(0,F37+G34-Setup!$C$15-G35) -> 0 | H37: =MAX(0,G37+H34-Setup!$C$15-H35) -> 0 | I37: =MAX(0,H37+I34-Setup!$C$15-I35) -> 0 | J37: =MAX(0,I37+J34-Setup!$C$15-J35) -> 0 | ... M37: =MAX(0,L37+M34-Setup!$C$15-M35) -> 0
A38: — Shortfall | B38: =MAX(0,Setup!$C$15+B35-Setup!$F$15-B34) -> 0 | C38: =MAX(0,Setup!$C$15+C35-B37-C34) -> 0 | D38: =MAX(0,Setup!$C$15+D35-C37-D34) -> 0 | E38: =MAX(0,Setup!$C$15+E35-D37-E34) -> 0 | F38: =MAX(0,Setup!$C$15+F35-E37-F34) -> 0 | G38: =MAX(0,Setup!$C$15+G35-F37-G34) -> 6 | H38: =MAX(0,Setup!$C$15+H35-G37-H34) -> 7 | I38: =MAX(0,Setup!$C$15+I35-H37-I34) -> 2 | J38: =MAX(0,Setup!$C$15+J35-I37-J34) -> 0 | ... M38: =MAX(0,Setup!$C$15+M35-L37-M34) -> 0
A40: Ilyra Holdings — Produce | B40: 3 | C40: 3 | D40: 3 | E40: 3 | F40: 3 | G40: 3 | H40: 3 | I40: 3 | J40: 3 | K40: 3 | L40: 3 | M40: 3
A41: — Buy | B41: 3 | C41: 3 | D41: 3 | E41: 3 | F41: 3 | G41: 3 | H41: 2 | I41: 3 | J41: 3 | K41: 3 | L41: 3 | M41: 3
A42: — Sell (from hoard) | B42: 0 | C42: 0 | D42: 0 | E42: 0 | F42: 0 | G42: 0 | H42: 0 | I42: 0 | J42: 0 | K42: 0 | L42: 0 | M42: 0
A43: — Credits ($) | B43: =Setup!$E$16+Setup!$B$8-B41*B7+(B40+B42)*B7 -> 160 | C43: =B43+Setup!$B$8-C41*C7+(C40+C42)*C7 -> 260 | D43: =C43+Setup!$B$8-D41*D7+(D40+D42)*D7 -> 360 | E43: =D43+Setup!$B$8-E41*E7+(E40+E42)*E7 -> 460 | F43: =E43+Setup!$B$8-F41*F7+(F40+F42)*F7 -> 560 | G43: =F43+Setup!$B$8-G41*G7+(G40+G42)*G7 -> 660 | H43: =G43+Setup!$B$8-H41*H7+(H40+H42)*H7 -> 798.48068 | I43: =H43+Setup!$B$8-I41*I7+(I40+I42)*I7 -> 898.48068 | J43: =I43+Setup!$B$8-J41*J7+(J40+J42)*J7 -> 998.48068 | ... M43: =L43+Setup!$B$8-M41*M7+(M40+M42)*M7 -> 1298.4807
A44: — Hoard | B44: =MAX(0,Setup!$F$16+B41-Setup!$C$16-B42) -> 0 | C44: =MAX(0,B44+C41-Setup!$C$16-C42) -> 0 | D44: =MAX(0,C44+D41-Setup!$C$16-D42) -> 0 | E44: =MAX(0,D44+E41-Setup!$C$16-E42) -> 0 | F44: =MAX(0,E44+F41-Setup!$C$16-F42) -> 0 | G44: =MAX(0,F44+G41-Setup!$C$16-G42) -> 0 | H44: =MAX(0,G44+H41-Setup!$C$16-H42) -> 0 | I44: =MAX(0,H44+I41-Setup!$C$16-I42) -> 0 | J44: =MAX(0,I44+J41-Setup!$C$16-J42) -> 0 | ... M44: =MAX(0,L44+M41-Setup!$C$16-M42) -> 0
A45: — Shortfall | B45: =MAX(0,Setup!$C$16+B42-Setup!$F$16-B41) -> 0 | C45: =MAX(0,Setup!$C$16+C42-B44-C41) -> 0 | D45: =MAX(0,Setup!$C$16+D42-C44-D41) -> 0 | E45: =MAX(0,Setup!$C$16+E42-D44-E41) -> 0 | F45: =MAX(0,Setup!$C$16+F42-E44-F41) -> 0 | G45: =MAX(0,Setup!$C$16+G42-F44-G41) -> 0 | H45: =MAX(0,Setup!$C$16+H42-G44-H41) -> 1 | I45: =MAX(0,Setup!$C$16+I42-H44-I41) -> 0 | J45: =MAX(0,Setup!$C$16+J42-I44-J41) -> 0 | ... M45: =MAX(0,Setup!$C$16+M42-L44-M41) -> 0

Sheet Dashboard
A1: DASHBOARD
A2: Charts read live from the Simulation sheet. Change inputs there and these update on recalculation.
